clock-divider/clock_divider.v
module clock_divider #(parameter WIDTH = 8)(
    input  wire             clk_in,
    input  wire             rst_n,      
    input  wire [WIDTH-1:0] divisor,    // N
    input  wire             clk_en,
    output wire             clk_out
);
 
    wire [WIDTH-1:0] n_eff = (divisor == {WIDTH{1'b0}}) ? {{(WIDTH-1){1'b0}}, 1'b1} : divisor;
    wire passthrough = (divisor == {WIDTH{1'b0}}) || (divisor == {{(WIDTH-1){1'b0}}, 1'b1});
    wire [WIDTH-1:0] high_thresh = (n_eff + 1'b1) >> 1;
 
    reg [WIDTH-1:0] count;
    reg             div_clk;
 
    always @(posedge clk_in or negedge rst_n) begin
        if (!rst_n) begin
            count   <= {WIDTH{1'b0}};
            div_clk <= 1'b0;
        end else if (clk_en) begin
            div_clk <= (count < high_thresh);
            if (count == n_eff - 1'b1)
                count <= {WIDTH{1'b0}};
            else
                count <= count + 1'b1;
        end else begin
            count   <= {WIDTH{1'b0}};
            div_clk <= 1'b0;
        end
    end
 assign clk_out = clk_en ? (passthrough ? clk_in : div_clk) : 1'b0;
endmodule

clock-divider/tb_clock_divider.v
`timescale 1ns/1ps
 
module tb_clock_divider;
 
    parameter WIDTH      = 8;
    parameter CLK_PERIOD = 10; // 100 MHz source clock
 
    reg               clk_in;
    reg               rst_n;
    reg  [WIDTH-1:0]  divisor;
    reg               clk_en;
    wire              clk_out;
 
    integer test_case;
 
    clock_divider #(.WIDTH(WIDTH)) DUT (
        .clk_in  (clk_in),
        .rst_n   (rst_n),
        .divisor (divisor),
        .clk_en  (clk_en),
        .clk_out (clk_out)
    );
 
    initial clk_in = 1'b0;
    always #(CLK_PERIOD/2) clk_in = ~clk_in;
 
    task do_reset;
        begin
            rst_n = 1'b0;
            #(CLK_PERIOD*2);
            rst_n = 1'b1;
        end
    endtask
 
    initial begin
        $dumpfile("tb_clock_divider.vcd");
        $dumpvars(0, tb_clock_divider);
 
        test_case = 0;
        rst_n     = 1'b0;
        clk_en    = 1'b0;
        divisor   = {WIDTH{1'b0}};
        #(CLK_PERIOD*2);
 
        // Case 1: Even Division, N = 4 
        test_case = 1;
        do_reset;
        divisor = 4; clk_en = 1'b1;
        #(CLK_PERIOD*20);
 
        //  Case 2: Odd Division, N = 5
        test_case = 2;
        do_reset;
        divisor = 5; clk_en = 1'b1;
        #(CLK_PERIOD*25);
 
        // Case 3: Divisor = 0 (pass-through) 
        test_case = 3;
        do_reset;
        divisor = 0; clk_en = 1'b1;
        #(CLK_PERIOD*10);
 
        // Case 4: Divisor = 1 (pass-through) 
        test_case = 4;
        do_reset;
        divisor = 1; clk_en = 1'b1;
        #(CLK_PERIOD*10);
 
        //  Case 5: clk_en gating mid-operation
        test_case = 5;
        do_reset;
        divisor = 4; clk_en = 1'b1;
        #(CLK_PERIOD*8);
        clk_en = 1'b0;
        #(CLK_PERIOD*8);
        clk_en = 1'b1;
        #(CLK_PERIOD*8);
 
        $display("All test cases completed.");
        $finish;
    end
 
endmodule

clock-divider/tb_clock_divider.vcd
$date
	Sat Jul 18 19:25:37 2026
$end
$version
	ModelSim Version 2020.1
$end
$timescale
	1ps
$end

$scope module tb_clock_divider $end
$var parameter 32 ! WIDTH $end
$var parameter 32 " CLK_PERIOD $end
$var reg 1 # clk_in $end
$var reg 1 $ rst_n $end
$var reg 8 % divisor [7:0] $end
$var reg 1 & clk_en $end
$var wire 1 ' clk_out $end
$var integer 32 ( test_case $end

$scope task do_reset $end
$upscope $end

$scope module DUT $end
$var parameter 32 ) WIDTH $end
$var wire 1 * clk_in $end
$var wire 1 + rst_n $end
$var wire 1 , divisor [7] $end
$var wire 1 - divisor [6] $end
$var wire 1 . divisor [5] $end
$var wire 1 / divisor [4] $end
$var wire 1 0 divisor [3] $end
$var wire 1 1 divisor [2] $end
$var wire 1 2 divisor [1] $end
$var wire 1 3 divisor [0] $end
$var wire 1 4 clk_en $end
$var wire 1 ' clk_out $end
$var wire 1 5 n_eff [7] $end
$var wire 1 6 n_eff [6] $end
$var wire 1 7 n_eff [5] $end
$var wire 1 8 n_eff [4] $end
$var wire 1 9 n_eff [3] $end
$var wire 1 : n_eff [2] $end
$var wire 1 ; n_eff [1] $end
$var wire 1 < n_eff [0] $end
$var wire 1 = passthrough $end
$var wire 1 > high_thresh [7] $end
$var wire 1 ? high_thresh [6] $end
$var wire 1 @ high_thresh [5] $end
$var wire 1 A high_thresh [4] $end
$var wire 1 B high_thresh [3] $end
$var wire 1 C high_thresh [2] $end
$var wire 1 D high_thresh [1] $end
$var wire 1 E high_thresh [0] $end
$var reg 8 F count [7:0] $end
$var reg 1 G div_clk $end
$upscope $end
$upscope $end
$enddefinitions $end
#0
$dumpvars
0#
0$
b0 %
0&
b0 F
0G
b1000 !
b1010 "
b1000 )
b0 (
0'
1<
0;
0:
09
08
07
06
05
1=
1E
0D
0C
0B
0A
0@
0?
0>
0*
0+
03
02
01
00
0/
0.
0-
0,
04
$end
#5000
1#
1*
#10000
0#
0*
#15000
1#
1*
#20000
b1 (
0#
0*
#25000
1#
1*
#30000
0#
0*
#35000
1#
1*
#40000
1$
b100 %
1&
0#
11
14
1'
0=
0<
1:
0'
0E
1D
1+
0*
#45000
1#
1*
1G
b1 F
1'
#50000
0#
0*
#55000
1#
1*
b10 F
#60000
0#
0*
#65000
1#
1*
0G
b11 F
0'
#70000
0#
0*
#75000
1#
1*
b0 F
#80000
0#
0*
#85000
1#
1*
1G
b1 F
1'
#90000
0#
0*
#95000
1#
1*
b10 F
#100000
0#
0*
#105000
1#
1*
0G
b11 F
0'
#110000
0#
0*
#115000
1#
1*
b0 F
#120000
0#
0*
#125000
1#
1*
1G
b1 F
1'
#130000
0#
0*
#135000
1#
1*
b10 F
#140000
0#
0*
#145000
1#
1*
0G
b11 F
0'
#150000
0#
0*
#155000
1#
1*
b0 F
#160000
0#
0*
#165000
1#
1*
1G
b1 F
1'
#170000
0#
0*
#175000
1#
1*
b10 F
#180000
0#
0*
#185000
1#
1*
0G
b11 F
0'
#190000
0#
0*
#195000
1#
1*
b0 F
#200000
0#
0*
#205000
1#
1*
1G
b1 F
1'
#210000
0#
0*
#215000
1#
1*
b10 F
#220000
0#
0*
#225000
1#
1*
0G
b11 F
0'
#230000
0#
0*
#235000
1#
1*
b0 F
#240000
b10 (
0$
0#
0+
0*
#245000
1#
1*
#250000
0#
0*
#255000
1#
1*
#260000
1$
b101 %
0#
13
1<
1E
1+
0*
#265000
1#
1*
1G
b1 F
1'
#270000
0#
0*
#275000
1#
1*
b10 F
#280000
0#
0*
#285000
1#
1*
b11 F
#290000
0#
0*
#295000
1#
1*
0G
b100 F
0'
#300000
0#
0*
#305000
1#
1*
b0 F
#310000
0#
0*
#315000
1#
1*
1G
b1 F
1'
#320000
0#
0*
#325000
1#
1*
b10 F
#330000
0#
0*
#335000
1#
1*
b11 F
#340000
0#
0*
#345000
1#
1*
0G
b100 F
0'
#350000
0#
0*
#355000
1#
1*
b0 F
#360000
0#
0*
#365000
1#
1*
1G
b1 F
1'
#370000
0#
0*
#375000
1#
1*
b10 F
#380000
0#
0*
#385000
1#
1*
b11 F
#390000
0#
0*
#395000
1#
1*
0G
b100 F
0'
#400000
0#
0*
#405000
1#
1*
b0 F
#410000
0#
0*
#415000
1#
1*
1G
b1 F
1'
#420000
0#
0*
#425000
1#
1*
b10 F
#430000
0#
0*
#435000
1#
1*
b11 F
#440000
0#
0*
#445000
1#
1*
0G
b100 F
0'
#450000
0#
0*
#455000
1#
1*
b0 F
#460000
0#
0*
#465000
1#
1*
1G
b1 F
1'
#470000
0#
0*
#475000
1#
1*
b10 F
#480000
0#
0*
#485000
1#
1*
b11 F
#490000
0#
0*
#495000
1#
1*
0G
b100 F
0'
#500000
0#
0*
#505000
1#
1*
b0 F
#510000
b11 (
0$
0#
0+
0*
#515000
1#
1*
#520000
0#
0*
#525000
1#
1*
#530000
1$
b0 %
0#
03
01
1=
0:
1'
0D
1+
0*
0'
#535000
1#
1*
1'
1G
#540000
0#
0*
0'
#545000
1#
1*
1'
#550000
0#
0*
0'
#555000
1#
1*
1'
#560000
0#
0*
0'
#565000
1#
1*
1'
#570000
0#
0*
0'
#575000
1#
1*
1'
#580000
0#
0*
0'
#585000
1#
1*
1'
#590000
0#
0*
0'
#595000
1#
1*
1'
#600000
0#
0*
0'
#605000
1#
1*
1'
#610000
0#
0*
0'
#615000
1#
1*
1'
#620000
0#
0*
0'
#625000
1#
1*
1'
#630000
b100 (
0$
0#
0+
0*
0'
0G
#635000
1#
1*
1'
#640000
0#
0*
0'
#645000
1#
1*
1'
#650000
1$
b1 %
0#
13
1+
0*
0'
#655000
1#
1*
1'
1G
#660000
0#
0*
0'
#665000
1#
1*
1'
#670000
0#
0*
0'
#675000
1#
1*
1'
#680000
0#
0*
0'
#685000
1#
1*
1'
#690000
0#
0*
0'
#695000
1#
1*
1'
#700000
0#
0*
0'
#705000
1#
1*
1'
#710000
0#
0*
0'
#715000
1#
1*
1'
#720000
0#
0*
0'
#725000
1#
1*
1'
#730000
0#
0*
0'
#735000
1#
1*
1'
#740000
0#
0*
0'
#745000
1#
1*
1'
#750000
b101 (
0$
0#
0+
0*
0'
0G
#755000
1#
1*
1'
#760000
0#
0*
0'
#765000
1#
1*
1'
#770000
1$
b100 %
0#
03
11
0=
0<
1:
0'
0E
1D
1+
0*
#775000
1#
1*
1G
b1 F
1'
#780000
0#
0*
#785000
1#
1*
b10 F
#790000
0#
0*
#795000
1#
1*
0G
b11 F
0'
#800000
0#
0*
#805000
1#
1*
b0 F
#810000
0#
0*
#815000
1#
1*
1G
b1 F
1'
#820000
0#
0*
#825000
1#
1*
b10 F
#830000
0#
0*
#835000
1#
1*
0G
b11 F
0'
#840000
0#
0*
#845000
1#
1*
b0 F
#850000
0&
0#
04
0*
#855000
1#
1*
#860000
0#
0*
#865000
1#
1*
#870000
0#
0*
#875000
1#
1*
#880000
0#
0*
#885000
1#
1*
#890000
0#
0*
#895000
1#
1*
#900000
0#
0*
#905000
1#
1*
#910000
0#
0*
#915000
1#
1*
#920000
0#
0*
#925000
1#
1*
#930000
1&
0#
14
0*
#935000
1#
1*
1G
b1 F
1'
#940000
0#
0*
#945000
1#
1*
b10 F
#950000
0#
0*
#955000
1#
1*
0G
b11 F
0'
#960000
0#
0*
#965000
1#
1*
b0 F
#970000
0#
0*
#975000
1#
1*
1G
b1 F
1'
#980000
0#
0*
#985000
1#
1*
b10 F
#990000
0#
0*
#995000
1#
1*
0G
b11 F
0'
